fs_dump/__init__.py
fs_dump/admin.py
fs_dump/apps.py
fs_dump/models.py
fs_dump/settings.py
fs_dump/utils.py
fs_dump/migrations/0001_initial.py
fs_dump/migrations/0002_remove_dump_output_alter_dump_database_dump_and_more.py
fs_dump/migrations/__init__.py
fs_dump/templates/admin/fs_dump/change_list_object_tools.html
django_fs_dump-1.0.0.dist-info/LICENSE
django_fs_dump-1.0.0.dist-info/METADATA
django_fs_dump-1.0.0.dist-info/WHEEL
django_fs_dump-1.0.0.dist-info/top_level.txt
django_fs_dump-1.0.0.dist-info/RECORD
